criteria_local/__init__.py
criteria_local/constants_src.py
criteria_local/criteria_local.py
criteria_local/criteria_profile.py
criteria_local/criterion.py
criteria_local-0.0.38.dist-info/METADATA
criteria_local-0.0.38.dist-info/WHEEL
criteria_local-0.0.38.dist-info/top_level.txt
criteria_local-0.0.38.dist-info/RECORD
