Metadata-Version: 2.4
Name: criteria-local
Version: 0.0.38
Home-page: https://github.com/circles-zone/criteria-local-python-package
Author: Circles
Author-email: info@circlez.ai
Classifier: Programming Language :: Python :: 3
Classifier: License :: Other/Proprietary License
Classifier: Operating System :: OS Independent
Requires-Dist: database-mysql-local>=0.1.10
Requires-Dist: logger-local>=0.0.175
Requires-Dist: opensearch-local>=0.0.8
Dynamic: author
Dynamic: author-email
Dynamic: classifier
Dynamic: description
Dynamic: description-content-type
Dynamic: home-page
Dynamic: requires-dist
